nrf24_op/__init__.py
nrf24_op/nrf24_op.py
nrf24_op-0.3.0.dist-info/LICENSE
nrf24_op-0.3.0.dist-info/METADATA
nrf24_op-0.3.0.dist-info/WHEEL
nrf24_op-0.3.0.dist-info/top_level.txt
nrf24_op-0.3.0.dist-info/RECORD
