Metadata-Version: 2.1
Name: nrf24-op
Version: 0.3.0
Summary: Python package for interacting with NRF24 wireless module
Home-page: UNKNOWN
Author: Nofal Elahi
License: MIT
Platform: UNKNOWN
License-File: LICENSE
Requires-Dist: OPi.GPIO
Requires-Dist: spidev
